{"id": "IT1281212", "title": "Users may be unable to access the Microsoft Intune web app from a managed Microsoft Edge iOS browser", "classification": "incident", "status": "serviceDegradation", "status_label": "Degraded", "service": "Microsoft Intune", "service_short": "Intune", "service_icon": "📱", "feature": "Microsoft Intune", "feature_group": "Microsoft Intune", "start_time": "2026-04-15T19:32:42+00:00", "end_time": null, "duration": null, "last_modified": "2026-04-16T00:37:21.517000+00:00", "impact": "Users may be unable to access the Microsoft Intune web app from a managed Microsoft Edge iOS browser.", "is_resolved": false, "updates": [{"timestamp": "2026-04-15T19:37:24.723000+00:00", "type": "regular", "content": "Title: Users may be unable to access the Microsoft Intune web app from a managed Microsoft Edge iOS browser\n\nUser impact: Users may be unable to access the Microsoft Intune web app from a managed Microsoft Edge iOS browser.\n\nMore info: The managed Microsoft Edge iOS browser may be displaying an error stating “Action Not Allowed” when trying to launch the Microsoft Intune web app.\n \nCurrent status: This is a continuation of IT1281088. We're continuing to creating a new build of the Microsoft Edge iOS browser that has the account management feature disabled to remediate impact. \n \nScope of impact: Any user attempting to access the Microsoft Intune web app from a managed Microsoft Edge iOS browser may be impacted.\n \nRoot cause: A code issue in the Mobile Application Management (MAM) SDK conflicts with a recently enabled account management feature, resulting in impact.\n \nNext update by: Wednesday, April 15, 2026, at 9:00 PM UTC"}, {"timestamp": "2026-04-15T20:21:54.230000+00:00", "type": "regular", "content": "Title: Users may be unable to access the Microsoft Intune web app from a managed Microsoft Edge iOS browser\n\nUser impact: Users may be unable to access the Microsoft Intune web app from a managed Microsoft Edge iOS browser.\n\nMore info: The managed Microsoft Edge iOS browser may be displaying an error stating “Action Not Allowed” when trying to launch the Microsoft Intune web app.\nThis only impacts those with iOS webapps created and targeted to users, and configured to launch in managed Microsoft Edge browser.\n \nCurrent status: We're testing a new build of the Microsoft Edge iOS browser that has the account management feature disabled to remediate impact. Once testing is complete, we'll determine the timeline for release and provide the version number.\n \nScope of impact: Any user who's attempting to access the created and targeted iOS Microsoft Intune web app that's configured to launch in a managed Microsoft Edge browser may be affected.\n \nRoot cause: A code issue in the Mobile Application Management (MAM) SDK conflicts with a recently enabled account management feature, resulting in impact.\n \nNext update by: Friday, April 17, 2026, at 3:00 AM UTC"}]}